{
  "viewport": {
    "x": 0,
    "y": 0,
    "zoom": 1
  },
  "nodes": [
    {
      "id": "intent",
      "x": 60,
      "y": 130
    },
    {
      "id": "research",
      "x": 280,
      "y": 130
    },
    {
      "id": "plan",
      "x": 500,
      "y": 130
    },
    {
      "id": "execute",
      "x": 720,
      "y": 130
    },
    {
      "id": "verify",
      "x": 940,
      "y": 130
    },
    {
      "id": "return",
      "x": 1160,
      "y": 130
    },
    {
      "id": "artifact_reverse_pass",
      "x": 340,
      "y": 330
    },
    {
      "id": "gate_reverse_pass",
      "x": 590,
      "y": 330
    },
    {
      "id": "artifact_tests_passed",
      "x": 820,
      "y": 330
    },
    {
      "id": "gate_tests",
      "x": 1070,
      "y": 330
    },
    {
      "id": "boundary_codex_worker",
      "x": 710,
      "y": 540
    }
  ]
}
